pyrozza/__init__.py
pyrozza/client.py
pyrozza/exceptions.py
pyrozza/tests/__init__.py
pyrozza/tests/conftest.py
pyrozza/tests/test_client.py
pyrozza-0.1.0.dist-info/LICENSE
pyrozza-0.1.0.dist-info/WHEEL
pyrozza-0.1.0.dist-info/METADATA
pyrozza-0.1.0.dist-info/RECORD
